src/mqi-api/v1/__init__.py
src/mqi-api/v1/api.py
mqi_api-0.0.1.dist-info/METADATA
mqi_api-0.0.1.dist-info/WHEEL
mqi_api-0.0.1.dist-info/licenses/LICENSE
mqi_api-0.0.1.dist-info/RECORD
