Metadata-Version: 2.1
Name: mqi-api
Version: 0.0.1
Summary: This is the official API of the MQI biasing box
Project-URL: Homepage, https://github.com/MQI-Software/mqi-api
Project-URL: Issues, https://github.com/MQI-Software/mqi-api/issues
Author-email: Filip Zlatoidsky <fillatino@gmail.com>
License-File: LICENSE
Classifier: License :: OSI Approved :: MIT License
Classifier: Operating System :: OS Independent
Classifier: Programming Language :: Python :: 3
Requires-Python: >=3.0
